{
  "node_id": "Z2",
  "examples": [
    {
      "learner_id": "sample-z2-blocked-01",
      "node_id": "Z2",
      "status": "blocked",
      "dependency_status": {
        "Z1": "secure"
      },
      "direct_accuracy": 0.53,
      "explanation_status": "weak",
      "transfer_status": "not_met",
      "retention_status": "not_due",
      "dominant_failure_modes": ["Z2-FM-02", "Z2-FM-03"],
      "recommended_interventions": [
        "highlight the target attribute visually",
        "ask which item does not belong and why"
      ],
      "last_verified_at": "2026-04-14",
      "review_state": "draft",
      "notes": "Can match some objects but changes the grouping rule mid-task."
    },
    {
      "learner_id": "sample-z2-secure-01",
      "node_id": "Z2",
      "status": "secure",
      "dependency_status": {
        "Z1": "secure"
      },
      "direct_accuracy": 0.95,
      "explanation_status": "met",
      "transfer_status": "met",
      "retention_status": "met",
      "dominant_failure_modes": [],
      "recommended_interventions": [],
      "last_verified_at": "2026-04-14",
      "review_state": "draft",
      "notes": "Matches and sorts by a stable attribute across objects and pictures."
    }
  ]
}
